<annotation>
	<folder>clover_img</folder>
	<filename>0014.jpg</filename>
	<path>/Users/choejongmun/Desktop/paper/1_Clover/dataset/clover_img/0014.jpg</path>
	<source>
		<database>Unknown</database>
	</source>
	<size>
		<width>276</width>
		<height>182</height>
		<depth>3</depth>
	</size>
	<segmented>0</segmented>
	<object>
		<name>4-clover</name>
		<pose>Unspecified</pose>
		<truncated>0</truncated>
		<difficult>0</difficult>
		<bndbox>
			<xmin>33</xmin>
			<ymin>63</ymin>
			<xmax>80</xmax>
			<ymax>104</ymax>
		</bndbox>
	</object>
</annotation>
